pieceofcake/__init__.py
pieceofcake/main.py
pieceofcake/version.py
pieceofcake-0.1a2.dist-info/LICENSE
pieceofcake-0.1a2.dist-info/METADATA
pieceofcake-0.1a2.dist-info/WHEEL
pieceofcake-0.1a2.dist-info/entry_points.txt
pieceofcake-0.1a2.dist-info/top_level.txt
pieceofcake-0.1a2.dist-info/zip-safe
pieceofcake-0.1a2.dist-info/RECORD
