Metadata-Version: 2.1
Name: pieceofcake
Version: 0.1a2
Summary: A user-friendly wrapper to cookiecutter
Home-page: https://github.com/astrofrog/pieceofcake
Author: Thomas Robitaille
Author-email: thomas.robitaille@gmail.com
License: BSD
Platform: UNKNOWN
Classifier: Intended Audience :: Developers
Classifier: Programming Language :: Python
Classifier: Programming Language :: Python :: 3
Classifier: Operating System :: OS Independent
Classifier: License :: OSI Approved :: BSD License
Requires-Python: >=3.6
Requires-Dist: click
Requires-Dist: cookiecutter
